{"hash":"2a94af61a7be8bec0e5f3391dc148e7e3ba2c755","data":{"keyboards":{"edges":[{"node":{"title":"Sofle","path":"/keyboards/sofle/","switch_socket":[{"id":"MX","title":"MX"}]}},{"node":{"title":"Misterium","path":"/keyboards/misterium/","switch_socket":[{"id":"MX","title":"MX"}]}},{"node":{"title":"Lily58","path":"/keyboards/lily58/","switch_socket":[{"id":"MX","title":"MX"},{"id":"Kailh","title":"Kailh"}]}},{"node":{"title":"Joynery","path":"/keyboards/joynery/","switch_socket":[{"id":"Choc","title":"Choc"}]}},{"node":{"title":"Discipline","path":"/keyboards/discipline/","switch_socket":[{"id":"MX","title":"MX"},{"id":"Choc","title":"Choc"}]}},{"node":{"title":"Corne","path":"/keyboards/corne/","switch_socket":[{"id":"MX","title":"MX"},{"id":"Choc","title":"Choc"}]}},{"node":{"title":"_33-Keyboard","path":"/keyboards/33-keyboard/","switch_socket":[{"id":"MX","title":"MX"}]}},{"node":{"title":"001Key","path":"/keyboards/001-key/","switch_socket":[{"id":"MX","title":"MX"},{"id":"Alps","title":"Alps"}]}}]}},"context":{"title":"Keyboards"}}